MANIFEST.in
README.md
description.rst
pyproject.toml
setup.py
jupyter-config/mosaik_docker_jl.json
mosaik_docker_jl/__init__.py
mosaik_docker_jl/_module_name.py
mosaik_docker_jl/_version.py
mosaik_docker_jl/comm.py
mosaik_docker_jl/execute.py
mosaik_docker_jl/handlers.py
mosaik_docker_jl.egg-info/PKG-INFO
mosaik_docker_jl.egg-info/SOURCES.txt
mosaik_docker_jl.egg-info/dependency_links.txt
mosaik_docker_jl.egg-info/not-zip-safe
mosaik_docker_jl.egg-info/requires.txt
mosaik_docker_jl.egg-info/top_level.txt
mosaik_docker_jl/labextension/jupyterlab-mosaik-docker-jl-0.1.1.tgz